LICENSE
wagtailperson/__init__.py
wagtailperson/admin.py
wagtailperson/apps.py
wagtailperson/blocks.py
wagtailperson/locale/fr/LC_MESSAGES/django.mo
wagtailperson/locale/fr/LC_MESSAGES/django.po
wagtailperson/locale/fr_CH/LC_MESSAGES/django.mo
wagtailperson/locale/fr_CH/LC_MESSAGES/django.po
wagtailperson/migrations/0001_initial.py
wagtailperson/migrations/0002_auto_20190820_1942.py
wagtailperson/migrations/0003_auto_20190821_1817.py
wagtailperson/migrations/0004_auto_20190821_2153.py
wagtailperson/migrations/0005_auto_20200220_1854.py
wagtailperson/migrations/0006_auto_20200416_1603.py
wagtailperson/migrations/0007_alter_person_options_alter_personindexpage_options_and_more.py
wagtailperson/migrations/__init__.py
wagtailperson/models.py
wagtailperson/static/wagtailperson/css/person.css
wagtailperson/static/wagtailperson/js/slug_from_person_name.js
wagtailperson/templates/wagtailperson/blocks/header.html
wagtailperson/templates/wagtailperson/blocks/link.html
wagtailperson/templates/wagtailperson/blocks/person.html
wagtailperson/templates/wagtailperson/person_index_page.html
wagtailperson/templates/wagtailperson/person_page.html
wagtailperson/tests.py
wagtailperson/views.py
wagtailperson/wagtail_hooks.py
wagtailperson-0.14.1.dist-info/LICENSE
wagtailperson-0.14.1.dist-info/WHEEL
wagtailperson-0.14.1.dist-info/METADATA
wagtailperson-0.14.1.dist-info/RECORD
