Metadata-Version: 2.1
Name: wagtailperson
Version: 0.14.1
Summary: Add a person and a persons index pages to Wagtail as well as a person block for StreamFields
Home-page: https://framagit.org/SebGen/wagtailperson
License: LGPLv3
Keywords: wagtailperson,wagtail,person
Author: Sébastien Gendre
Author-email: seb@k-7.ch
Requires-Python: >=3.9,<4.0
Classifier: Development Status :: 4 - Beta
Classifier: Framework :: Django
Classifier: Framework :: Wagtail
Classifier: Framework :: Wagtail :: 2
Classifier: License :: OSI Approved :: GNU Lesser General Public License v3 (LGPLv3)
Classifier: License :: Other/Proprietary License
Classifier: Operating System :: OS Independent
Classifier: Programming Language :: Python
Classifier: Programming Language :: Python :: 3
Classifier: Programming Language :: Python :: 3.10
Classifier: Programming Language :: Python :: 3.9
Classifier: Topic :: Internet
Classifier: Topic :: Software Development :: Libraries :: Python Modules
Requires-Dist: wagtail (>=4.2,<5.0)
Project-URL: Repository, https://framagit.org/SebGen/wagtailperson
